ecceran/__init__.py
ecceran/__main__.py
ecceran/utils.py
ecceran-0.1.1.dist-info/entry_points.txt
ecceran-0.1.1.dist-info/WHEEL
ecceran-0.1.1.dist-info/METADATA
ecceran-0.1.1.dist-info/RECORD
