Metadata-Version: 2.1
Name: ecceran
Version: 0.1.1
Summary: Simple ECC encrypt decrypt
Author: hfrada
Author-email: madefrada@gmail.com
Requires-Python: >=3.9,<4.0
Classifier: Programming Language :: Python :: 3
Classifier: Programming Language :: Python :: 3.10
Classifier: Programming Language :: Python :: 3.9
Requires-Dist: coincurve (==16.0.0)
Requires-Dist: pycryptodome (==3.12.0)
